{"_id":{"$oid":"60b97b10390d4510b52c84f5"},"site_blacklisted_channels":[],"ap_blacklisted_channels":[],"conf_source":"radio-ai","status":"blacklist","note":"","site_id":"60b8ca58390d450643a48f3d","radio":null}
{"_id":{"$oid":"60baccd6390d4510b52c9c3d"},"coupling":[{"source":"e0:63:da:06:58:74-FULL","target":"f0:9f:c2:a9:1c:a9-FULL","rssi":{"$numberDouble":"-104.0"}},{"source":"f0:9f:c2:a9:1c:a9-FULL","target":"e0:63:da:06:58:74-FULL","rssi":{"$numberDouble":"-103.0"}}],"date":{"$date":{"$numberLong":"1622854870100"}},"radio":"na","site_id":"60b8ca58390d450643a48f3d","status":"coupling","note":""}
{"_id":{"$oid":"60baccd6390d4510b52c9c40"},"radio_table":[{"device_mac":"e0:63:da:06:58:74","name":"wifi1","channel":{"$numberInt":"36"},"backup_channel":{"$numberInt":"0"},"width":{"$numberInt":"40"},"tx_power":{"$numberInt":"20"},"tx_power_mode":"auto"},{"device_mac":"f0:9f:c2:a9:1c:a9","name":"wifi1","channel":{"$numberInt":"40"},"backup_channel":{"$numberInt":"0"},"width":{"$numberInt":"40"},"tx_power":{"$numberInt":"20"},"tx_power_mode":"auto"}],"date":{"$date":{"$numberLong":"1622854800032"}},"satisfaction":{"$numberDouble":"100.0"},"status":"historical","conf_source":"radio-ai","use_defaults":true,"radios":["ng","na"],"optimize":["channel"],"channels_ng":[],"channels_na":[],"ht_modes_ng":[{"$numberInt":"20"}],"ht_modes_na":[{"$numberInt":"20"},{"$numberInt":"40"}],"useXY":false,"frequency":"daily","exclude_devices":[],"satisfaction_table":[{"device_mac":"f0:9f:c2:a9:1c:a9","satisfaction":{"$numberDouble":"99.26342710997443"}},{"device_mac":"e0:63:da:06:58:74","satisfaction":{"$numberDouble":"96.33878113098743"}}],"run_id":{"$numberLong":"1622854800009"},"num_sta":{"$numberDouble":"0.034537684537684535"},"calculation_time":{"$numberLong":"-1"},"note":"","site_id":"60b8ca58390d450643a48f3d","radio":"na"}
{"_id":{"$oid":"60c012d6390d4510b52d0143"},"coupling":[{"source":"e0:63:da:06:58:74-FULL","target":"f0:9f:c2:a9:1c:a9-FULL","rssi":{"$numberDouble":"-101.0"}},{"source":"f0:9f:c2:a9:1c:a9-FULL","target":"e0:63:da:06:58:74-FULL","rssi":{"$numberDouble":"-104.0"}}],"date":{"$date":{"$numberLong":"1623200470042"}},"radio":"ng","site_id":"60b8ca58390d450643a48f3d","status":"coupling","note":""}
{"_id":{"$oid":"60c0131c390d4510b52d0148"},"coupling":[{"source":"e0:63:da:06:58:74-FULL","target":"f0:9f:c2:a9:1c:a9-FULL","rssi":{"$numberDouble":"-103.0"}},{"source":"f0:9f:c2:a9:1c:a9-FULL","target":"e0:63:da:06:58:74-FULL","rssi":{"$numberDouble":"-99.0"}}],"date":{"$date":{"$numberLong":"1623200540188"}},"radio":"na","site_id":"60b8ca58390d450643a48f3d","status":"coupling","note":""}
{"_id":{"$oid":"60c0131c390d4510b52d014a"},"radio_table":[{"device_mac":"e0:63:da:06:58:74","name":"wifi1","channel":{"$numberInt":"36"},"backup_channel":{"$numberInt":"0"},"width":{"$numberInt":"40"},"tx_power":{"$numberInt":"20"},"tx_power_mode":"auto"},{"device_mac":"f0:9f:c2:a9:1c:a9","name":"wifi1","channel":{"$numberInt":"40"},"backup_channel":{"$numberInt":"0"},"width":{"$numberInt":"40"},"tx_power":{"$numberInt":"20"},"tx_power_mode":"auto"}],"date":{"$date":{"$numberLong":"1622854870551"}},"satisfaction":{"$numberDouble":"98.49520769740148"},"status":"historical","conf_source":"radio-ai","wireless_uplink_aps":[],"use_defaults":true,"radios":["ng","na"],"optimize":["channel"],"channels_ng":[],"channels_na":[],"ht_modes_ng":[{"$numberInt":"20"}],"ht_modes_na":[{"$numberInt":"20"},{"$numberInt":"40"}],"useXY":false,"frequency":"daily","exclude_devices":[],"satisfaction_table":[{"device_mac":"f0:9f:c2:a9:1c:a9","satisfaction":{"$numberDouble":"96.86433587330045"}},{"device_mac":"e0:63:da:06:58:74","satisfaction":{"$numberDouble":"96.47987649991957"}}],"run_id":{"$numberLong":"1623200400012"},"num_sta":{"$numberDouble":"0.43505552376830015"},"calculation_time":{"$numberLong":"70530"},"note":"","site_id":"60b8ca58390d450643a48f3d","radio":"na"}
{"_id":{"$oid":"60c0131c390d4510b52d014b"},"radio_table":[{"device_mac":"e0:63:da:06:58:74","name":"wifi0","channel":{"$numberInt":"6"},"backup_channel":{"$numberInt":"0"},"width":{"$numberInt":"20"},"tx_power":{"$numberInt":"17"},"tx_power_mode":"auto"},{"device_mac":"f0:9f:c2:a9:1c:a9","name":"wifi0","channel":{"$numberInt":"6"},"backup_channel":{"$numberInt":"0"},"width":{"$numberInt":"20"},"tx_power":{"$numberInt":"17"},"tx_power_mode":"auto"}],"date":{"$date":{"$numberLong":"1623200400024"}},"satisfaction":{"$numberDouble":"100.0"},"status":"historical","conf_source":"radio-ai","use_defaults":true,"radios":["ng","na"],"optimize":["channel"],"channels_ng":[],"channels_na":[],"ht_modes_ng":[{"$numberInt":"20"}],"ht_modes_na":[{"$numberInt":"20"},{"$numberInt":"40"}],"useXY":false,"frequency":"daily","exclude_devices":[],"satisfaction_table":[{"device_mac":"e0:63:da:06:58:74","satisfaction":{"$numberDouble":"93.0"}}],"run_id":{"$numberLong":"1623200400012"},"num_sta":{"$numberDouble":"0.0005605451547009989"},"calculation_time":{"$numberLong":"-1"},"note":"","site_id":"60b8ca58390d450643a48f3d","radio":"ng"}
{"_id":{"$oid":"60c16456390d4510b52d10f0"},"coupling":[{"source":"e0:63:da:06:58:74-FULL","target":"f0:9f:c2:a9:1c:a9-FULL","rssi":{"$numberDouble":"-100.0"}},{"source":"f0:9f:c2:a9:1c:a9-FULL","target":"e0:63:da:06:58:74-FULL","rssi":{"$numberDouble":"-104.0"}}],"date":{"$date":{"$numberLong":"1623286870036"}},"radio":"ng","site_id":"60b8ca58390d450643a48f3d","status":"coupling","note":""}
{"_id":{"$oid":"60c16456390d4510b52d10f3"},"radio_table":[{"device_mac":"e0:63:da:06:58:74","name":"wifi1","channel":{"$numberInt":"36"},"backup_channel":{"$numberInt":"0"},"width":{"$numberInt":"40"},"tx_power":{"$numberInt":"20"},"tx_power_mode":"auto"},{"device_mac":"f0:9f:c2:a9:1c:a9","name":"wifi1","channel":{"$numberInt":"40"},"backup_channel":{"$numberInt":"0"},"width":{"$numberInt":"40"},"tx_power":{"$numberInt":"20"},"tx_power_mode":"auto"}],"date":{"$date":{"$numberLong":"1623200470175"}},"satisfaction":{"$numberDouble":"94.93803195460654"},"status":"historical","conf_source":"radio-ai","wireless_uplink_aps":[],"use_defaults":true,"radios":["ng","na"],"optimize":["channel"],"channels_ng":[],"channels_na":[],"ht_modes_ng":[{"$numberInt":"20"}],"ht_modes_na":[{"$numberInt":"20"},{"$numberInt":"40"}],"useXY":false,"frequency":"daily","exclude_devices":[],"satisfaction_table":[{"device_mac":"f0:9f:c2:a9:1c:a9","satisfaction":{"$numberDouble":"95.26126126126127"}},{"device_mac":"e0:63:da:06:58:74","satisfaction":{"$numberDouble":"95.07385906714342"}}],"run_id":{"$numberLong":"1623286800007"},"num_sta":{"$numberDouble":"0.25367424242424247"},"calculation_time":{"$numberLong":"70131"},"note":"","site_id":"60b8ca58390d450643a48f3d","radio":"na"}
{"_id":{"$oid":"60c16456390d4510b52d10f4"},"radio_table":[{"device_mac":"e0:63:da:06:58:74","name":"wifi0","channel":{"$numberInt":"6"},"backup_channel":{"$numberInt":"0"},"width":{"$numberInt":"20"},"tx_power":{"$numberInt":"17"},"tx_power_mode":"auto"},{"device_mac":"f0:9f:c2:a9:1c:a9","name":"wifi0","channel":{"$numberInt":"6"},"backup_channel":{"$numberInt":"0"},"width":{"$numberInt":"20"},"tx_power":{"$numberInt":"17"},"tx_power_mode":"auto"}],"date":{"$date":{"$numberLong":"1623200470154"}},"satisfaction":{"$numberDouble":"100.0"},"status":"historical","conf_source":"radio-ai","wireless_uplink_aps":[],"use_defaults":true,"radios":["ng","na"],"optimize":["channel"],"channels_ng":[],"channels_na":[],"ht_modes_ng":[{"$numberInt":"20"}],"ht_modes_na":[{"$numberInt":"20"},{"$numberInt":"40"}],"useXY":false,"frequency":"daily","exclude_devices":[],"satisfaction_table":[{"device_mac":"e0:63:da:06:58:74","satisfaction":{"$numberDouble":"100.0"}}],"run_id":{"$numberLong":"1623286800007"},"num_sta":{"$numberDouble":"0.0033964646464646462"},"calculation_time":{"$numberLong":"70142"},"note":"","site_id":"60b8ca58390d450643a48f3d","radio":"ng"}
{"_id":{"$oid":"60c2b590390d4510b52d2114"},"calculation_time":{"$numberLong":"23"},"conf_source":"radio-ai","status":"calc_time","note":"","site_id":"60b8ca58390d450643a48f3d","radio":"ng"}
{"_id":{"$oid":"60c2b5d6390d4510b52d2124"},"coupling":[{"source":"e0:63:da:06:58:74-FULL","target":"f0:9f:c2:a9:1c:a9-FULL","rssi":{"$numberDouble":"-103.0"}},{"source":"f0:9f:c2:a9:1c:a9-FULL","target":"e0:63:da:06:58:74-FULL","rssi":{"$numberDouble":"-101.0"}}],"date":{"$date":{"$numberLong":"1623373270062"}},"radio":"na","site_id":"60b8ca58390d450643a48f3d","status":"coupling","note":""}
{"_id":{"$oid":"60c2b5d6390d4510b52d2127"},"radio_table":[{"device_mac":"e0:63:da:06:58:74","name":"wifi1","channel":{"$numberInt":"36"},"backup_channel":{"$numberInt":"0"},"width":{"$numberInt":"40"},"tx_power":{"$numberInt":"20"},"tx_power_mode":"auto"},{"device_mac":"f0:9f:c2:a9:1c:a9","name":"wifi1","channel":{"$numberInt":"40"},"backup_channel":{"$numberInt":"0"},"width":{"$numberInt":"40"},"tx_power":{"$numberInt":"20"},"tx_power_mode":"auto"}],"date":{"$date":{"$numberLong":"1623286870115"}},"satisfaction":{"$numberDouble":"99.08674082982564"},"status":"historical","conf_source":"radio-ai","wireless_uplink_aps":[],"use_defaults":true,"radios":["ng","na"],"optimize":["channel"],"channels_ng":[],"channels_na":[],"ht_modes_ng":[{"$numberInt":"20"}],"ht_modes_na":[{"$numberInt":"20"},{"$numberInt":"40"}],"useXY":false,"frequency":"daily","exclude_devices":[],"satisfaction_table":[{"device_mac":"f0:9f:c2:a9:1c:a9","satisfaction":{"$numberDouble":"89.17676767676767"}},{"device_mac":"e0:63:da:06:58:74","satisfaction":{"$numberDouble":"96.14061655635784"}}],"run_id":{"$numberLong":"1623373200009"},"num_sta":{"$numberDouble":"0.6719191919191919"},"calculation_time":{"$numberLong":"21"},"note":"","site_id":"60b8ca58390d450643a48f3d","radio":"na"}
{"_id":{"$oid":"60c2b5d6390d4510b52d2128"},"radio_table":[{"device_mac":"e0:63:da:06:58:74","name":"wifi0","channel":{"$numberInt":"6"},"backup_channel":{"$numberInt":"0"},"width":{"$numberInt":"20"},"tx_power":{"$numberInt":"17"},"tx_power_mode":"auto"},{"device_mac":"f0:9f:c2:a9:1c:a9","name":"wifi0","channel":{"$numberInt":"6"},"backup_channel":{"$numberInt":"0"},"width":{"$numberInt":"20"},"tx_power":{"$numberInt":"17"},"tx_power_mode":"auto"}],"date":{"$date":{"$numberLong":"1623286800025"}},"satisfaction":{"$numberDouble":"84.71691559569295"},"status":"historical","conf_source":"radio-ai","wireless_uplink_aps":[],"use_defaults":true,"radios":["ng","na"],"optimize":["channel"],"channels_ng":[],"channels_na":[],"ht_modes_ng":[{"$numberInt":"20"}],"ht_modes_na":[{"$numberInt":"20"},{"$numberInt":"40"}],"useXY":false,"frequency":"daily","exclude_devices":[],"satisfaction_table":[{"device_mac":"f0:9f:c2:a9:1c:a9","satisfaction":{"$numberDouble":"86.90625"}},{"device_mac":"e0:63:da:06:58:74","satisfaction":{"$numberDouble":"91.75303972656468"}}],"run_id":{"$numberLong":"1623373200009"},"num_sta":{"$numberDouble":"0.0363510101010101"},"calculation_time":{"$numberLong":"70088"},"note":"","site_id":"60b8ca58390d450643a48f3d","radio":"ng"}
{"_id":{"$oid":"60c2b5d6390d4510b52d212a"},"status":"active","site_id":"60b8ca58390d450643a48f3d","date":{"$date":{"$numberLong":"1623373200031"}},"conf_source":"radio-ai","radio_table":[{"device_mac":"e0:63:da:06:58:74","name":"wifi0","channel":{"$numberInt":"6"},"backup_channel":{"$numberInt":"0"},"width":{"$numberInt":"20"},"tx_power":{"$numberInt":"17"},"tx_power_mode":"auto"},{"device_mac":"f0:9f:c2:a9:1c:a9","name":"wifi0","channel":{"$numberInt":"6"},"backup_channel":{"$numberInt":"0"},"width":{"$numberInt":"20"},"tx_power":{"$numberInt":"17"},"tx_power_mode":"auto"}],"calculation_time":{"$numberLong":"23"},"run_id":{"$numberLong":"1623373200010"},"use_defaults":true,"radios":["ng","na"],"optimize":["channel"],"channels_ng":[],"channels_na":[],"ht_modes_ng":[{"$numberInt":"20"}],"ht_modes_na":[{"$numberInt":"20"},{"$numberInt":"40"}],"useXY":false,"frequency":"daily","exclude_devices":[],"note":"","radio":"ng"}
{"_id":{"$oid":"60c6aa10390d4502395564b0"},"radio_table":[{"device_mac":"e0:63:da:06:58:74","name":"wifi1","channel":{"$numberInt":"36"},"backup_channel":{"$numberInt":"0"},"width":{"$numberInt":"40"},"tx_power":{"$numberInt":"20"},"tx_power_mode":"auto"},{"device_mac":"f0:9f:c2:a9:1c:a9","name":"wifi1","channel":{"$numberInt":"40"},"backup_channel":{"$numberInt":"0"},"width":{"$numberInt":"40"},"tx_power":{"$numberInt":"20"},"tx_power_mode":"auto"}],"date":{"$date":{"$numberLong":"1623373270128"}},"satisfaction":{"$numberDouble":"99.26215747885887"},"status":"historical","conf_source":"radio-ai","wireless_uplink_aps":[],"use_defaults":true,"radios":["ng","na"],"optimize":["channel"],"channels_ng":[],"channels_na":[],"ht_modes_ng":[{"$numberInt":"20"}],"ht_modes_na":[{"$numberInt":"20"},{"$numberInt":"40"}],"useXY":false,"frequency":"daily","exclude_devices":[],"satisfaction_table":[{"device_mac":"f0:9f:c2:a9:1c:a9","satisfaction":{"$numberDouble":"92.71332547500771"}},{"device_mac":"e0:63:da:06:58:74","satisfaction":{"$numberDouble":"97.7931918684735"}}],"run_id":{"$numberLong":"1623632400045"},"num_sta":{"$numberDouble":"0.26003787878787876"},"calculation_time":{"$numberLong":"70095"},"note":"","site_id":"60b8ca58390d450643a48f3d","radio":"na"}
{"_id":{"$oid":"60c7fbd6390d450239557652"},"coupling":[{"source":"e0:63:da:06:58:74-FULL","target":"f0:9f:c2:a9:1c:a9-FULL","rssi":{"$numberDouble":"-95.0"}},{"source":"f0:9f:c2:a9:1c:a9-FULL","target":"e0:63:da:06:58:74-FULL","rssi":{"$numberDouble":"-99.0"}}],"date":{"$date":{"$numberLong":"1623718870153"}},"radio":"na","site_id":"60b8ca58390d450643a48f3d","status":"coupling","note":""}
{"_id":{"$oid":"60c7fbd6390d450239557653"},"radio_table":[{"device_mac":"e0:63:da:06:58:74","name":"wifi1","channel":{"$numberInt":"36"},"backup_channel":{"$numberInt":"0"},"width":{"$numberInt":"40"},"tx_power":{"$numberInt":"20"},"tx_power_mode":"auto"},{"device_mac":"f0:9f:c2:a9:1c:a9","name":"wifi1","channel":{"$numberInt":"40"},"backup_channel":{"$numberInt":"0"},"width":{"$numberInt":"40"},"tx_power":{"$numberInt":"20"},"tx_power_mode":"auto"}],"date":{"$date":{"$numberLong":"1623718870607"}},"fitness":{"$numberDouble":"0.09"},"satisfaction":{"$numberDouble":"93.58078118064805"},"status":"running","conf_source":"radio-ai","use_defaults":true,"radios":["ng","na"],"optimize":["channel"],"channels_ng":[],"channels_na":[],"ht_modes_ng":[{"$numberInt":"20"}],"ht_modes_na":[{"$numberInt":"20"},{"$numberInt":"40"}],"useXY":false,"frequency":"daily","exclude_devices":[],"note":"","site_id":"60b8ca58390d450643a48f3d","radio":"na"}
{"_id":{"$oid":"60c7fbd6390d450239557655"},"radio_table":[{"device_mac":"e0:63:da:06:58:74","name":"wifi1","channel":{"$numberInt":"36"},"backup_channel":{"$numberInt":"0"},"width":{"$numberInt":"40"},"tx_power":{"$numberInt":"20"},"tx_power_mode":"auto"},{"device_mac":"f0:9f:c2:a9:1c:a9","name":"wifi1","channel":{"$numberInt":"40"},"backup_channel":{"$numberInt":"0"},"width":{"$numberInt":"40"},"tx_power":{"$numberInt":"20"},"tx_power_mode":"auto"}],"date":{"$date":{"$numberLong":"1623632400110"}},"satisfaction":{"$numberDouble":"93.58078118064805"},"status":"historical","conf_source":"radio-ai","wireless_uplink_aps":[],"use_defaults":true,"radios":["ng","na"],"optimize":["channel"],"channels_ng":[],"channels_na":[],"ht_modes_ng":[{"$numberInt":"20"}],"ht_modes_na":[{"$numberInt":"20"},{"$numberInt":"40"}],"useXY":false,"frequency":"daily","exclude_devices":[],"satisfaction_table":[{"device_mac":"f0:9f:c2:a9:1c:a9","satisfaction":{"$numberDouble":"90.58714932830289"}},{"device_mac":"e0:63:da:06:58:74","satisfaction":{"$numberDouble":"95.85559730236933"}}],"run_id":{"$numberLong":"1623718800008"},"num_sta":{"$numberDouble":"0.22757575757575757"},"calculation_time":{"$numberLong":"33"},"note":"","site_id":"60b8ca58390d450643a48f3d","radio":"na"}
{"_id":{"$oid":"60c7fbd6390d450239557656"},"radio_table":[{"device_mac":"f0:9f:c2:a9:1c:a9","name":"wifi1","channel":{"$numberInt":"40"},"backup_channel":{"$numberInt":"0"},"width":{"$numberInt":"40"},"tx_power":{"$numberInt":"20"},"tx_power_mode":"auto"},{"device_mac":"e0:63:da:06:58:74","name":"wifi1","channel":{"$numberInt":"36"},"backup_channel":{"$numberInt":"0"},"width":{"$numberInt":"40"},"tx_power":{"$numberInt":"20"},"tx_power_mode":"auto"}],"status":"active","site_id":"60b8ca58390d450643a48f3d","date":{"$date":{"$numberLong":"1623718870614"}},"conf_source":"radio-ai","wireless_uplink_aps":[],"calculation_time":{"$numberLong":"70594"},"run_id":{"$numberLong":"1623718800009"},"use_defaults":true,"radios":["ng","na"],"optimize":["channel"],"channels_ng":[],"channels_na":[],"ht_modes_ng":[{"$numberInt":"20"}],"ht_modes_na":[{"$numberInt":"20"},{"$numberInt":"40"}],"useXY":false,"frequency":"daily","exclude_devices":[],"note":"","radio":"na"}
